kcorrect/__init__.py
kcorrect/_version.py
kcorrect/fitter.py
kcorrect/kcorrect.py
kcorrect/response.py
kcorrect/template.py
kcorrect/utils.py
kcorrect/data/basel/ReadMe
kcorrect/data/basel/lcbsun.ori
kcorrect/data/basel/lcbvega.ascii
kcorrect/data/basel/lcbvega.ori
kcorrect/data/basel/models.dat
kcorrect/data/basel/read_lcb.f
kcorrect/data/responses/FORS2_R_ccd_atm.dat
kcorrect/data/responses/FORS_B_ccd_atm.dat
kcorrect/data/responses/FORS_I_ccd_atm.dat
kcorrect/data/responses/FORS_V_ccd_atm.dat
kcorrect/data/responses/README
kcorrect/data/responses/SOFI_J_atm.dat
kcorrect/data/responses/SOFI_Ks_atm.dat
kcorrect/data/responses/alhambra_768.dat
kcorrect/data/responses/alhambra_799.dat
kcorrect/data/responses/alhambra_830.dat
kcorrect/data/responses/alhambra_861.dat
kcorrect/data/responses/alhambra_892.dat
kcorrect/data/responses/alhambra_923.dat
kcorrect/data/responses/alhambra_954.dat
kcorrect/data/responses/alhambra_H.dat
kcorrect/data/responses/alhambra_J.dat
kcorrect/data/responses/alhambra_KS.dat
kcorrect/data/responses/alhambra_f365w.dat
kcorrect/data/responses/alhambra_f396w.dat
kcorrect/data/responses/alhambra_f427w.dat
kcorrect/data/responses/alhambra_f458w.dat
kcorrect/data/responses/alhambra_f489w.dat
kcorrect/data/responses/alhambra_f520w.dat
kcorrect/data/responses/alhambra_f551w.dat
kcorrect/data/responses/alhambra_f582w.dat
kcorrect/data/responses/alhambra_f613w.dat
kcorrect/data/responses/alhambra_f644w.dat
kcorrect/data/responses/alhambra_f675w.dat
kcorrect/data/responses/alhambra_f706w.dat
kcorrect/data/responses/alhambra_f737w.dat
kcorrect/data/responses/alhambra_f768w.dat
kcorrect/data/responses/alhambra_f799w.dat
kcorrect/data/responses/alhambra_f830w.dat
kcorrect/data/responses/alhambra_f861w.dat
kcorrect/data/responses/alhambra_f892w.dat
kcorrect/data/responses/alhambra_f923w.dat
kcorrect/data/responses/alhambra_f954w.dat
kcorrect/data/responses/bass_g.dat
kcorrect/data/responses/bass_r.dat
kcorrect/data/responses/bessell_B.dat
kcorrect-5.1.8.dist-info/licenses/LICENSE
kcorrect-5.1.8.dist-info/METADATA
kcorrect-5.1.8.dist-info/WHEEL
kcorrect-5.1.8.dist-info/top_level.txt
kcorrect-5.1.8.dist-info/RECORD
