Metadata-Version: 2.4
Name: kcorrect
Version: 5.1.8
Author-email: "Michael R. Blanton" <michael.blanton@gmail.com>
License: BSD 3-Clause License
Project-URL: Source Code, https://github.com/blanton144/kcorrect
Classifier: Development Status :: 4 - Beta
Classifier: License :: OSI Approved :: BSD License
Classifier: Intended Audience :: Developers
Classifier: Intended Audience :: Science/Research
Classifier: Operating System :: OS Independent
Classifier: Programming Language :: Python
Requires-Python: >=3.9
License-File: LICENSE
Requires-Dist: matplotlib>=3.5.2
Requires-Dist: numpy>=1.18.1
Requires-Dist: scipy>=1.8.1
Requires-Dist: astropy>=3.0.0
Provides-Extra: dev
Requires-Dist: jupyter; extra == "dev"
Requires-Dist: pre-commit; extra == "dev"
Requires-Dist: pytest; extra == "dev"
Requires-Dist: pytest-cov; extra == "dev"
Requires-Dist: ruff; extra == "dev"
Dynamic: license-file
